Metadata-Version: 1.1
Name: pylogger-discord
Version: 0.0.121
Summary: A simple logger for production apps
Home-page: UNKNOWN
Author: Sebastian Tuyu
Author-email: contact@sebastiantuyu.com
License: MIT
Keywords: DISCORD,LOGGER,CONSOLE
Platform: UNKNOWN
Requires: dotenv
